shape/__init__.py
shape/angles.py
shape/bbox.py
shape/ellipse.py
shape/ep.py
shape/point.py
shape/polygon.py
shape/rotated_bbox.py
shape/shape.py
shape/transformableregion.py
shape-0.1.1.dist-info/LICENSE.md
shape-0.1.1.dist-info/METADATA
shape-0.1.1.dist-info/WHEEL
shape-0.1.1.dist-info/top_level.txt
shape-0.1.1.dist-info/zip-safe
shape-0.1.1.dist-info/RECORD
